podkit/__init__.py
podkit/_version.py
podkit/constants.py
podkit/backends/__init__.py
podkit/backends/base.py
podkit/backends/docker.py
podkit/core/__init__.py
podkit/core/events.py
podkit/core/manager.py
podkit/core/models.py
podkit/core/session.py
podkit/monitors/__init__.py
podkit/monitors/base.py
podkit/monitors/health.py
podkit/monitors/orphans.py
podkit/processes/__init__.py
podkit/processes/manager.py
podkit/processes/models.py
podkit/processes/monitor.py
podkit/utils/__init__.py
podkit/utils/lifecycle.py
podkit/utils/mounts.py
podkit/utils/network.py
podkit/utils/paths.py
podkit/utils/ports.py
podkit-0.7.3.dist-info/METADATA
podkit-0.7.3.dist-info/WHEEL
podkit-0.7.3.dist-info/top_level.txt
podkit-0.7.3.dist-info/RECORD
