Metadata-Version: 2.4
Name: podkit
Version: 0.7.3
Summary: Container management library with backend abstraction for sandboxed execution
Author: Navari Team
Requires-Python: >=3.11
Requires-Dist: docker>=7.1.0
Requires-Dist: pydantic>=2.12.5
Provides-Extra: dev
Requires-Dist: build>=1.2.2; extra == "dev"
Requires-Dist: twine>=6.0.0; extra == "dev"
Requires-Dist: pytest>=9.0.2; extra == "dev"
Requires-Dist: pytest-timeout>=2.2.0; extra == "dev"
Requires-Dist: pytest-xdist>=3.5.0; extra == "dev"
Requires-Dist: ruff>=0.14.10; extra == "dev"
Requires-Dist: pylint>=4.0.4; extra == "dev"
Requires-Dist: setuptools-scm>=9.2.2; extra == "dev"
